.gitignore
License
Makefile
README.md
__init__.py
requirements.txt
setup.py
configuratorpy/__init__.py
configuratorpy/exceptions.py
configuratorpy/helpers.py
configuratorpy/models.py
configuratorpy.egg-info/PKG-INFO
configuratorpy.egg-info/SOURCES.txt
configuratorpy.egg-info/dependency_links.txt
configuratorpy.egg-info/requires.txt
configuratorpy.egg-info/top_level.txt
configuratorpy/plugins/__init__.py
configuratorpy/plugins/base.py
configuratorpy/plugins/env.py
configuratorpy/plugins/seq.py
scripts/detect.sh
tests/main.py
tests/test_configurator.py
tests/test_helpers.py
tests/data/config.toml
tests/data/env.conf
version/__init__.py
version/__main__.py
version/value.py