Metadata-Version: 2.1
Name: configuratorpy
Version: 0.0.5
Summary: This is the package that will provides the configuration functions using jinja2 templates
Home-page: https://github.com/guitarpoet/python-configurator
Author: Jack
Author-email: jack@thinkingcloud.info
License: Apache 2.0
Platform: UNKNOWN
Classifier: Programming Language :: Python
Classifier: Programming Language :: Python :: 3.7
Classifier: Programming Language :: Python :: 3.8
Classifier: Programming Language :: Python :: 3.9
Classifier: License :: OSI Approved :: Apache Software License
Classifier: Operating System :: OS Independent
